pyxk/__init__.py
pyxk/cryptor.py
pyxk/lazy_loader.py
pyxk/progress.py
pyxk/client/__init__.py
pyxk/client/_base.py
pyxk/client/_typedef.py
pyxk/client/client.py
pyxk/m3u8/__init__.py
pyxk/m3u8/_download.py
pyxk/m3u8/_entry_point.py
pyxk/m3u8/_main.py
pyxk/m3u8/_parser.py
pyxk/m3u8/_typedef.py
pyxk/request/__init__.py
pyxk/request/_api.py
pyxk/request/_base.py
pyxk/request/_entry_point.py
pyxk/request/_sessions.py
pyxk/request/_typedef.py
pyxk/utils/__init__.py
pyxk/utils/chardetector.py
pyxk/utils/main.py
pyxk/utils/typedef.py
pyxk/utils/useragent.py
pyxk-0.7.4.dist-info/LICENSE
pyxk-0.7.4.dist-info/METADATA
pyxk-0.7.4.dist-info/WHEEL
pyxk-0.7.4.dist-info/entry_points.txt
pyxk-0.7.4.dist-info/top_level.txt
pyxk-0.7.4.dist-info/RECORD
