Metadata-Version: 2.1
Name: pyxk
Version: 0.7.4
Summary: pyxk
Home-page: 
Author: kai139
Author-email: 925330867@qq.com
Classifier: Programming Language :: Python :: 3
Classifier: License :: OSI Approved :: MIT License
Classifier: Operating System :: OS Independent
Requires-Python: >=3.9
License-File: LICENSE
Requires-Dist: requests
Requires-Dist: pycryptodome
Requires-Dist: rich
Requires-Dist: m3u8
Requires-Dist: aiohttp
Requires-Dist: aiofiles
Requires-Dist: click
Requires-Dist: parsel
Requires-Dist: chardet
Requires-Dist: user-agents
Requires-Dist: faker
